UART_design.sv
// Code your design here

module Duplex_UART(tx_data_in,tx_data_out,rx_data_in,rx_data_out,clk,start);
  input start, clk;
  input [6:0] tx_data_in;
  output tx_data_out;
  input rx_data_in;
  output [6:0] rx_data_out ;
  
  uart_tx u_tx(start,clk,tx_data_in,tx_data_out);
  uart_rx u_rx(rx_data_in,clk,rx_data_out);
  
endmodule

// UART Transmitter 
module uart_tx(start,clk,data_in,data_out);
  input start ,clk ;
  input [6:0] data_in;
  output data_out;
  
  reg active;
  integer count;
  wire [7:0] data_in_temp = {data_in,1'b1} ; 
  
  assign data_out = active ? data_in_temp[count] : 1'bx ;
  
  always @(posedge start) begin 
	active = 1;
    count = 0 ;
  end
  
  always @(posedge clk) begin
    
    if(count==7) begin
      active=0;
      count = 0;
    end
    if(active==1) begin
      count = count + 1;
    end
    
  end
  
endmodule

// UART Receiver 
module uart_rx(data_in,clk,data_out);
  input data_in, clk;
  output reg [6:0] data_out=0;
  reg [7:0] data_out_temp=0;
  integer count=0 ;
  reg active=0 ;
  
  always @(posedge data_in) begin 
    if(active==0) begin
      count = 0 ;
      active = 1 ;
    end
  end
  
  always @(posedge clk) begin 
    if(count==8) begin 
      count = 0 ;
      active = 0 ;
    end
    if(active==1) begin 
      data_out_temp[count] <= data_in;
      count = count + 1 ;
    end
  end
  
  always @(negedge active) begin 
    data_out = data_out_temp[7:1];
  end
  
endmodule

uart_rx_testbench.sv
// Code your testbench here
// or browse Examples
// Code your testbench here
// or browse Examples
module test_uart_rx;
  reg data_in,clk;
  wire [6:0] data_out;
  
  uart_rx u_rx(data_in,clk,data_out);
  
  initial begin 
    // Dump waves
    $dumpfile("dump.vcd");
    $dumpvars(1);
    data_in = 0 ;
    clk = 0 ;
    #5;
    data_in = 1;
    #6;
    data_in = 0;
    #6;
    data_in = 1;
    #6;
    data_in = 1;
    #6;
    data_in = 0;
    #6;
    data_in = 1;
    #6;
    data_in = 0;
    #6;
    data_in = 1;
    #6;
    // data ahead of this would go into next packet 
    data_in = 1;
    #12;
    $finish;
  end
  
  always begin 
    #3;
    clk=~clk;
  end
  
endmodule

uart_rx_dump.vcd
$date
Sun Jul  9 08:51:33 2023
$end
$version
Riviera-PRO Version 2022.04.117.8517
$end
$timescale
1 ns
$end

$scope module test_uart_rx $end
$var wire 7 ! data_out [6:0] $end
$var reg 1 " data_in $end
$var reg 1 # clk $end
$upscope $end

$enddefinitions $end
$dumpvars
b0 !
0"
0#
$end
#3
1#
#5
1"
#6
0#
#9
1#
#11
0"
#12
0#
#15
1#
#17
1"
#18
0#
#21
1#
#24
0#
#27
1#
#29
0"
#30
0#
#33
1#
#35
1"
#36
0#
#39
1#
#41
0"
#42
0#
#45
1#
#47
1"
#48
0#
#51
1#
#54
0#
#57
1#
b1010110 !
